[
  {
    "id": "1777262162458",
    "date": "2026-04-27T03:56:02.458Z",
    "status": "success",
    "fileName": "backup-2026-04-27-09-25.zip",
    "fileSize": 22867407,
    "message": "Backup completed successfully",
    "attempts": 1,
    "error": null
  },
  {
    "id": "1777141808818",
    "date": "2026-04-25T18:30:08.818Z",
    "status": "success",
    "fileName": "backup-2026-04-26-00-00.zip",
    "fileSize": 23816620,
    "message": "Backup completed successfully",
    "attempts": 1,
    "error": null
  },
  {
    "id": "1777140832295",
    "date": "2026-04-25T18:13:52.295Z",
    "status": "success",
    "fileName": "backup-2026-04-25-23-43.zip",
    "fileSize": 23816356,
    "message": "Backup completed successfully",
    "attempts": 1,
    "error": null
  }
]